[
    {
        "info": "2.8 x 4 x 0.4 inches 2.9 ounces 4 ounces SanDisk B006EKJCWM Item can be shipped within U.S. This item is not eligible for international shipping. Imported (China) SDSSDX-120G-G25 4.4 out of 5 stars December 8, 2011 None None", 
        "ratings": {
            "2 star": "4%", 
            "1 star": "5%", 
            "4 star": "10%", 
            "3 star": "4%", 
            "5 star": "77%"
        }, 
        "price": "$ 4 9 . 9 9", 
        "original_price": "$ 4 9 . 9 9", 
        "question_count": "27", 
        "category": "1292116011", 
        "asin": "B006EKJCWM", 
        "review_count": "1008", 
        "name": "SDSSDX-120G-G25 SanDisk Extreme SSD 120GB SATA 6.0 Gb-s2.5-Inch Solid State Drive (SSD)", 
        "url": "http://www.amazon.com/dp/B006EKJCWM", 
        "brand": "SanDisk"
    }, 
    {
        "info": "B019DMRJM2 0.0 out of 5 stars 9.1 ounces ( ) Currently, item can be shipped only within the U.S. and to APO/FPO addresses. For APO/FPO shipments, please check with the manufacturer regarding warranty and support issues. This item is not eligible for international shipping. January 18, 2016 400 GB Serial Attached SCSI 3 HEWLETT PACKARD ENTERPRISE N9X95A N9X95A PC 7.2 ounces 9 x 7 x 5 inches 9 x 7 x 5 inches Aluminium, Black 400 Serial Attached SCSI", 
        "ratings": {}, 
        "price": "$990.00", 
        "original_price": "$990.00", 
        "question_count": "0", 
        "category": "1292116011", 
        "asin": "B019DMRJM2", 
        "review_count": "0", 
        "name": "HEWLETT PACKARD ENTERPRISE N9X95A Mixed Use 400GB 2 1/2\" SFF SAS Internal Solid State Drive", 
        "url": "http://www.amazon.com/dp/B019DMRJM2", 
        "brand": "HEWLETT PACKARD ENTERPRISE"
    }, 
    {
        "info": "B013FDABIO 0.0 out of 5 stars 9.6 ounces Currently, item can be shipped only within the U.S. and to APO/FPO addresses. For APO/FPO shipments, please check with the manufacturer regarding warranty and support issues. This item is not eligible for international shipping. August 4, 2015 Samsung MZ-7LM1T9E MZ-7LM1T9E 2.2 ounces 3.9 x 0.4 x 2.8 inches 3.94 x 0.39 x 2.76 inches Black 1920 None", 
        "ratings": {}, 
        "price": "$ 4 5 0 . 5 9", 
        "original_price": "$ 4 5 0 . 5 9", 
        "question_count": "0", 
        "category": "1292116011", 
        "asin": "B013FDABIO", 
        "review_count": "0", 
        "name": "Samsung Pm863 1.92 Tb 2.5 Internal Solid State Drive 510 Mb/s Maximum Read & 475 Mb/s Maximum Write Transfer Rate", 
        "url": "http://www.amazon.com/dp/B013FDABIO", 
        "brand": "Samsung"
    }, 
    {
        "info": "1 x 1 x 1 inches 1 ounces 1 ounces ( ) Hardkernel B01LX1KQV0 Korea, Republic of 0.0 out of 5 stars September 29, 2016 None None", 
        "ratings": {}, 
        "price": "$69.99", 
        "original_price": "$69.99", 
        "question_count": "0", 
        "category": "1292116011", 
        "asin": "B01LX1KQV0", 
        "review_count": "0", 
        "name": "32GB eMMC for ODROID XU4 XU3 U3", 
        "url": "http://www.amazon.com/dp/B01LX1KQV0", 
        "brand": "ODROID"
    }, 
    {
        "info": "9 x 8 x 3 inches 1.8 pounds 1.8 pounds ( ) B01DE6ULD2 0F14688 0.0 out of 5 stars March 24, 2016 None None", 
        "ratings": {}, 
        "price": "$169.00", 
        "original_price": "$169.00", 
        "question_count": "0", 
        "category": "1292116011", 
        "asin": "B01DE6ULD2", 
        "review_count": "0", 
        "name": "HGST Ultrastar 7K4000 4 TB 3.5\" Internal Hard Drive - SATA - 7200 - 64 MB Buffer RPM 64MB 3.5IN 25.4MM 8.0 512N", 
        "url": "http://www.amazon.com/dp/B01DE6ULD2", 
        "brand": "Hitachi"
    }, 
    {
        "info": "2.8 x 3.9 x 0.3 inches 1.6 ounces 1.6 ounces ( ) Other World Computing B00JHCUMTG OWCSSD7P6G120 3.1 out of 5 stars April 7, 2014 None None", 
        "ratings": {
            "2 star": "50%", 
            "4 star": "50%"
        }, 
        "price": "$87.50", 
        "original_price": "$87.50", 
        "question_count": "0", 
        "category": "1292116011", 
        "asin": "B00JHCUMTG", 
        "review_count": "2", 
        "name": "OWC / Other World Computing 120GB Mercury Extreme Pro 2.5\" SATA 6G Solid State Drive, SATA 6 Gb/s and 3 Gb/s Interface, 559 MB/s Max Read Speed, 527 MB/s Max Write Speed", 
        "url": "http://www.amazon.com/dp/B00JHCUMTG", 
        "brand": "OWC"
    }, 
    {
        "info": "4 x 3 x 1 inches B01N53USCO 0.0 out of 5 stars November 18, 2016 None None", 
        "ratings": {}, 
        "price": "$89.99", 
        "original_price": "$89.99", 
        "question_count": "0", 
        "category": "1292116011", 
        "asin": "B01N53USCO", 
        "review_count": "0", 
        "name": "MyDigitalSSD Super Boot 2 (SB2) 50mm mSATA SATA III (6G) SSD Solid State Drive (256GB)", 
        "url": "http://www.amazon.com/dp/B01N53USCO", 
        "brand": "MyDigitalSSD"
    }, 
    {
        "info": "6.3 x 4.4 x 2.7 inches 5.6 ounces 5.6 ounces ( ) Intel B00Y046Z06 Pro 1500 0.0 out of 5 stars May 21, 2015 None None", 
        "ratings": {}, 
        "price": "$99.00", 
        "original_price": "$99.00", 
        "question_count": "0", 
        "category": "1292116011", 
        "asin": "B00Y046Z06", 
        "review_count": "0", 
        "name": "Replacement For 7mm HP 735235-001 790942-001 Laptop Intel Pro 1500 SSDSC2BF180A4H 180GB SSD HDD 2.5\" SATA MLC Hard Disk Solid State Drive", 
        "url": "http://www.amazon.com/dp/B00Y046Z06", 
        "brand": "Intel"
    }, 
    {
        "info": "B00KGZNGIW 4.6 out of 5 stars 4.8 ounces Item can be shipped within U.S. This item is not eligible for international shipping. May 27, 2014 256 GB Corsair CSSD-F256GBLX pc, laptop 3.2 ounces 4.4 x 5.4 x 0.6 inches 4.4 x 5.4 x 0.6 inches Black 256 5 volts", 
        "ratings": {
            "4 star": "20%", 
            "3 star": "3%", 
            "5 star": "77%"
        }, 
        "price": "$ 7 . 1 8", 
        "original_price": "$ 7 . 1 8", 
        "question_count": "6", 
        "category": "1292116011", 
        "asin": "B00KGZNGIW", 
        "review_count": "39", 
        "name": "Cosair Force LX Series Solid State Disk (SSD) 256GB 2.5-Inch (CSSD-F256GBLX)", 
        "url": "http://www.amazon.com/dp/B00KGZNGIW", 
        "brand": "Corsair"
    }, 
    {
        "info": "3.9 x 2.8 x 0.3 inches 0.6 ounces 0.6 ounces ( ) Ableconn B01HR0PKJQ IU2-M2132 3.1 out of 5 stars June 30, 2016 None None", 
        "ratings": {
            "1 star": "50%", 
            "5 star": "50%"
        }, 
        "price": "$37.99", 
        "original_price": "$37.99", 
        "question_count": "5", 
        "category": "1292116011", 
        "asin": "B01HR0PKJQ", 
        "review_count": "4", 
        "name": "Ableconn IU2-M2132 M.2 NVMe SSD to U.2 (SFF-8639) 2.5-Inch SSD Adapter with Aluminum Frame Bracket - Turn M.2 NVMe SSD as U.2 (SFF-8639) 2.5\" Solid State Drive", 
        "url": "http://www.amazon.com/dp/B01HR0PKJQ", 
        "brand": "Ableconn"
    }, 
    {
        "info": "None 5.7 x 3.4 x 2.2 inches 5.6 ounces 5.6 ounces Toshiba B00JRJKFJQ 4994736 5.0 out of 5 stars April 17, 2014 None", 
        "ratings": {}, 
        "price": "\n \n \n", 
        "original_price": "\n \n \n", 
        "question_count": "0", 
        "category": "1292116011", 
        "asin": "B00JRJKFJQ", 
        "review_count": "0", 
        "name": null, 
        "url": "http://www.amazon.com/dp/B00JRJKFJQ", 
        "brand": "None"
    }, 
    {
        "info": "5.5 x 1.6 x 0.4 inches 7 ounces 8 ounces ( ) Other World Computing B00KTKMRR0 OWCSSDA2A6K120 5.0 out of 5 stars June 6, 2014 None None", 
        "ratings": {
            "5 star": "100%"
        }, 
        "price": "$107.75", 
        "original_price": "$107.75", 
        "question_count": "0", 
        "category": "1292116011", 
        "asin": "B00KTKMRR0", 
        "review_count": "2", 
        "name": "OWC 120GB Aura SSD and Envoy Storage Solution for MacBook Air 2012", 
        "url": "http://www.amazon.com/dp/B00KTKMRR0", 
        "brand": "OWC"
    }, 
    {
        "info": "6 x 4 x 2 inches SIB B008UTK5A8 B008UTK5A8 4.7 out of 5 stars August 8, 2012 None None", 
        "ratings": {
            "4 star": "25%", 
            "5 star": "75%"
        }, 
        "price": "$39.80", 
        "original_price": "$39.80", 
        "question_count": "3", 
        "category": "1292116011", 
        "asin": "B008UTK5A8", 
        "review_count": "8", 
        "name": "NEW 500GB 2.5\" Hard Disk Drive for HP Pavilion DV6700 Laptop", 
        "url": "http://www.amazon.com/dp/B008UTK5A8", 
        "brand": "SIB"
    }, 
    {
        "info": "4.2 x 2.5 x 0.9 inches 0.8 ounces 0.8 ounces Crucial B00O071V3E MTFDDAT128MBF-1AN12ABYY 0.0 out of 5 stars September 28, 2014 None None", 
        "ratings": {}, 
        "price": "$ 9 7 . 9 9", 
        "original_price": "$ 9 7 . 9 9", 
        "question_count": "0", 
        "category": "1292116011", 
        "asin": "B00O071V3E", 
        "review_count": "0", 
        "name": "Crucial Technology MTFDDAT128MBF-1AN12ABYY Micron M600 128gb Msata Ssd", 
        "url": "http://www.amazon.com/dp/B00O071V3E", 
        "brand": "Crucial"
    }, 
    {
        "info": "2.8 x 4 x 0.3 inches 4 ounces 1 pounds ( ) MICRON B01MTZ5KLS MTFDDAK480TBY-1AR1ZA 0.0 out of 5 stars December 10, 2016 None None", 
        "ratings": {}, 
        "price": "$287.12", 
        "original_price": "$287.12", 
        "question_count": "0", 
        "category": "1292116011", 
        "asin": "B01MTZ5KLS", 
        "review_count": "0", 
        "name": "5100 Eco 480Gb Sata 2.5 Tcg Disabled", 
        "url": "http://www.amazon.com/dp/B01MTZ5KLS", 
        "brand": "Micron"
    }, 
    {
        "info": "B01M3R9JJG 0.0 out of 5 stars 2.9 ounces ( ) Currently, item can be shipped only within the U.S. and to APO/FPO addresses. For APO/FPO shipments, please check with the manufacturer regarding warranty and support issues. This item can be shipped to select countries outside of the U.S. October 17, 2016 128 GB Transcend TS128GSSD230S 2.2 ounces 3.9 x 2.7 x 0.3 inches 3.9 x 2.7 x 0.27 inches Silver 128", 
        "ratings": {}, 
        "price": "$59.99", 
        "original_price": "$59.99", 
        "question_count": "0", 
        "category": "1292116011", 
        "asin": "B01M3R9JJG", 
        "review_count": "0", 
        "name": "Transcend TS128GSSD230S Information 128GB 3D TLC SATA III 6GB/S 2.5\" Solid State Drive 230 2.5\"", 
        "url": "http://www.amazon.com/dp/B01M3R9JJG", 
        "brand": "Transcend"
    }, 
    {
        "info": "B00UL50J6O 4.3 out of 5 stars 6.1 ounces Currently, item can be shipped only within the U.S. and to APO/FPO addresses. For APO/FPO shipments, please check with the manufacturer regarding warranty and support issues. This item is not eligible for international shipping. March 12, 2015 120 GB Intel SSDSC2BW120H6R5 pc, laptop 1 pounds 4.5 x 1.8 x 5.6 inches 4.5 x 1.8 x 5.6 inches 120", 
        "ratings": {
            "2 star": "8%", 
            "4 star": "25%", 
            "5 star": "67%"
        }, 
        "price": "$ 5 0 . 9 9", 
        "original_price": "$ 5 0 . 9 9", 
        "question_count": "0", 
        "category": "1292116011", 
        "asin": "B00UL50J6O", 
        "review_count": "12", 
        "name": "Intel 535 Series 120GB 2.5-Inch Internal Solid State Drive SSDSC2BW120H6R5", 
        "url": "http://www.amazon.com/dp/B00UL50J6O", 
        "brand": "Intel"
    }, 
    {
        "info": "B00JXKIEMO 3.9 out of 5 stars 1.4 pounds ( ) Item can be shipped within U.S. This item is not eligible for international shipping. May 4, 2014 7.1 inches 480 GB OCZ STORAGE SOLUTIONS RVD350-FHPX28-480G 10.9 ounces 7.1 x 5 x 0.8 inches 7.12 x 4.97 x 0.85 inches Grey 480", 
        "ratings": {
            "2 star": "3%", 
            "1 star": "12%", 
            "4 star": "9%", 
            "3 star": "9%", 
            "5 star": "67%"
        }, 
        "price": "$448.90", 
        "original_price": "$448.90", 
        "question_count": "10", 
        "category": "1292116011", 
        "asin": "B00JXKIEMO", 
        "review_count": "33", 
        "name": "OCZ Storage Solutions RevoDrive 350 Series 480GB PCI Express Generation 2 x 8 Solid State Drive RVD350-FHPX28-480G", 
        "url": "http://www.amazon.com/dp/B00JXKIEMO", 
        "brand": "OCZ STORAGE SOLUTIONS"
    }, 
    {
        "info": "3.9 x 2.8 x 0.3 inches 2.9 ounces 3.4 ounces ( ) Mushkin Enhanced B01H64DKMW MKNSSDTR250GB 0.0 out of 5 stars September 26, 2016 None None", 
        "ratings": {}, 
        "price": "$103.41", 
        "original_price": "$103.41", 
        "question_count": "0", 
        "category": "1292116011", 
        "asin": "B01H64DKMW", 
        "review_count": "0", 
        "name": "Mushkin TRIACTOR 250GB Internal Solid State Drive (SSD) - 2.5 Inch - SATA III - 6Gb/s - TLC - 7mm - MKNSSDTR250GB", 
        "url": "http://www.amazon.com/dp/B01H64DKMW", 
        "brand": "Mushkin"
    }, 
    {
        "info": "B0118CA5V2 3.9 out of 5 stars 0.8 ounces ( ) July 8, 2015 ZTC 0.8 ounces 2 x 1.2 x 0.1 inches ZTC-MS001 64GB ZTC-MS001-064G None", 
        "ratings": {
            "1 star": "22%", 
            "4 star": "14%", 
            "5 star": "64%"
        }, 
        "price": "$34.45", 
        "original_price": "$34.45", 
        "question_count": "3", 
        "category": "1292116011", 
        "asin": "B0118CA5V2", 
        "review_count": "14", 
        "name": "ZTC 64GB Bulwark V2 mSATA 6G 50mm Enhanced SSD Solid State Drive Model ZTC-MS001-64G", 
        "url": "http://www.amazon.com/dp/B0118CA5V2", 
        "brand": "ZTC"
    }, 
    {
        "info": "B018FXP0TO 0.0 out of 5 stars November 24, 2015 1.2 TB None", 
        "ratings": {}, 
        "price": "$1364.95", 
        "original_price": "$1364.95", 
        "question_count": "0", 
        "category": "1292116011", 
        "asin": "B018FXP0TO", 
        "review_count": "0", 
        "name": "Intel DC S3710 2.5'' 1.2TB SATA III MLC Internal Solid State Drive (SSD) SSDSC2BA012T401", 
        "url": "http://www.amazon.com/dp/B018FXP0TO", 
        "brand": "Intel"
    }, 
    {
        "info": "None None None", 
        "ratings": {}, 
        "price": null, 
        "original_price": null, 
        "question_count": "0", 
        "category": "1292116011", 
        "asin": "B011J7YST6", 
        "review_count": "0", 
        "name": null, 
        "url": "http://www.amazon.com/dp/B011J7YST6", 
        "brand": "None"
    }, 
    {
        "info": "B0150O7NRI 0.0 out of 5 stars 1 pounds ( ) Currently, item can be shipped only within the U.S. and to APO/FPO addresses. For APO/FPO shipments, please check with the manufacturer regarding warranty and support issues. This item can be shipped to select countries outside of the U.S. September 6, 2015 200 GB HP 804639-B21 804639-B21 12 ounces 7.5 x 8.7 x 5.1 inches 7.48 x 8.66 x 5.12 inches 200", 
        "ratings": {}, 
        "price": "$309.16", 
        "original_price": "$309.16", 
        "question_count": "0", 
        "category": "1292116011", 
        "asin": "B0150O7NRI", 
        "review_count": "0", 
        "name": "HP 804639-B21 Write Intensive-2 - Solid state drive - 200 GB - hot-swap - 2.5 inch SFF - SATA 6Gb/s - with HP SmartDrive carrier", 
        "url": "http://www.amazon.com/dp/B0150O7NRI", 
        "brand": "HP"
    }, 
    {
        "info": "None None None", 
        "ratings": {}, 
        "price": null, 
        "original_price": null, 
        "question_count": "0", 
        "category": "1292116011", 
        "asin": "B019O0KLFA", 
        "review_count": "0", 
        "name": null, 
        "url": "http://www.amazon.com/dp/B019O0KLFA", 
        "brand": "None"
    }, 
    {
        "info": "None None None", 
        "ratings": {}, 
        "price": null, 
        "original_price": null, 
        "question_count": "0", 
        "category": "1292116011", 
        "asin": "B0055ZPJC4", 
        "review_count": "0", 
        "name": null, 
        "url": "http://www.amazon.com/dp/B0055ZPJC4", 
        "brand": "None"
    }, 
    {
        "info": "None None None", 
        "ratings": {}, 
        "price": null, 
        "original_price": null, 
        "question_count": "0", 
        "category": "1292116011", 
        "asin": "B00V4P27QU", 
        "review_count": "0", 
        "name": null, 
        "url": "http://www.amazon.com/dp/B00V4P27QU", 
        "brand": "None"
    }, 
    {
        "info": "None None None", 
        "ratings": {}, 
        "price": null, 
        "original_price": null, 
        "question_count": "0", 
        "category": "1292116011", 
        "asin": "B00SITMJYK", 
        "review_count": "0", 
        "name": null, 
        "url": "http://www.amazon.com/dp/B00SITMJYK", 
        "brand": "None"
    }, 
    {
        "info": "None None None", 
        "ratings": {}, 
        "price": null, 
        "original_price": null, 
        "question_count": "0", 
        "category": "1292116011", 
        "asin": "B00858CYKS", 
        "review_count": "0", 
        "name": null, 
        "url": "http://www.amazon.com/dp/B00858CYKS", 
        "brand": "None"
    }, 
    {
        "info": "5.5 x 1.6 x 0.4 inches 1.6 ounces 1.6 ounces Mushkin B00CJZMXAO MKNSSDCR240GB-7 4.1 out of 5 stars November 26, 2013 None None", 
        "ratings": {
            "1 star": "15%", 
            "4 star": "8%", 
            "3 star": "8%", 
            "5 star": "69%"
        }, 
        "price": "$ 7 9 . 9 9", 
        "original_price": "$ 7 9 . 9 9", 
        "question_count": "0", 
        "category": "1292116011", 
        "asin": "B00CJZMXAO", 
        "review_count": "13", 
        "name": "Mushkin MKNSSDCR240GB-7 Chronos 2.5\" 240GB SATA III 7mm SSD Solid State Drive", 
        "url": "http://www.amazon.com/dp/B00CJZMXAO", 
        "brand": "Mushkin"
    }
]